pybehance/__init__.py
pybehance/downloader.py
pybehance/settings.py
pybehance-0.2.5.dist-info/LICENSE
pybehance-0.2.5.dist-info/WHEEL
pybehance-0.2.5.dist-info/METADATA
pybehance-0.2.5.dist-info/RECORD
