Metadata-Version: 2.1
Name: pybehance
Version: 0.2.5
Summary: pybehance package
Author-email: Semenov Artur <juicehq@yandex.ru>
Classifier: License :: OSI Approved :: MIT License
Requires-Dist: beautifulsoup4==4.11.1
Requires-Dist: httpx==0.23.1
Project-URL: Home, https://github.com/meanother/behance-py
